django_rich/__init__.py
django_rich/py.typed
django_rich/test.py
django_rich/management/__init__.py
django_rich/management/commands/__init__.py
django_rich/management/commands/shell.py
django_rich-2.1.0.dist-info/licenses/LICENSE
django_rich-2.1.0.dist-info/METADATA
django_rich-2.1.0.dist-info/WHEEL
django_rich-2.1.0.dist-info/top_level.txt
django_rich-2.1.0.dist-info/RECORD
